{
  "project_info": {
    "project_number": "1025639696663",
    "firebase_url": "https://neomifashion.firebaseio.com",
    "project_id": "neomifashion",
    "storage_bucket": "neomifashion.appspot.com"
  },
  "client": [
    {
      "client_info": {
        "mobilesdk_app_id": "1:1025639696663:android:d2e02e66d2fe84809b8f52",
        "android_client_info": {
          "package_name": "com.ciesto.evaafashion"
        }
      },
      "oauth_client": [
        {
          "client_id": "1025639696663-1jfb4s3o8ppva5hbcjea1pu2k04kmii2.apps.googleusercontent.com",
          "client_type": 3
        }
      ],
      "api_key": [
        {
          "current_key": "AIzaSyBDH5fgW2Zd0MgP30eibSLx34OJExP0Exs"
        }
      ],
      "services": {
        "appinvite_service": {
          "other_platform_oauth_client": [
            {
              "client_id": "1025639696663-1jfb4s3o8ppva5hbcjea1pu2k04kmii2.apps.googleusercontent.com",
              "client_type": 3
            }
          ]
        }
      }
    },
    {
      "client_info": {
        "mobilesdk_app_id": "1:1025639696663:android:940654657d4d30389b8f52",
        "android_client_info": {
          "package_name": "com.ciesto.evaafashion"
        }
      },
      "oauth_client": [
        {
          "client_id": "1025639696663-1jfb4s3o8ppva5hbcjea1pu2k04kmii2.apps.googleusercontent.com",
          "client_type": 3
        }
      ],
      "api_key": [
        {
          "current_key": "AIzaSyBDH5fgW2Zd0MgP30eibSLx34OJExP0Exs"
        }
      ],
      "services": {
        "appinvite_service": {
          "other_platform_oauth_client": [
            {
              "client_id": "1025639696663-1jfb4s3o8ppva5hbcjea1pu2k04kmii2.apps.googleusercontent.com",
              "client_type": 3
            }
          ]
        }
      }
    }
  ],
  "configuration_version": "1"
}